{
    "nombre": "Cafetera Espresso Pro",
    "descripcion": "Disfruta de un café de calidad profesional en casa con nuestra Cafetera Espresso Pro.",
    "caracteristicas": [
        "Presión de 15 bares para una extracción perfecta",
        "Espumador de leche integrado",
        "Depósito de agua de 1.5 litros",
        "Compatible con café molido y cápsulas",
        "Diseño compacto y elegante"
    ],
    "precio": "399,900 COP",
    "envio": "Envío gratis a toda Colombia con pago contra entrega"
}
